[
    {
        "title": "Exploding Kittens",
        "capacity": 12,
        "image": "https://explodingkittens.com/img/social/ek_Facebook_OG_Images_Home.png",
        "date": "31st of January at 4pm",
        "latitude": 51.520470,
        "longitude": -0.087260
    },
    {
        "title": "Football game",
        "capacity": 5,
        "image": "https://images.freeimages.com/images/large-previews/30d/soccer-balls-1548508.jpg",
        "date": "2nd of February at 2pm",
        "latitude": 51.521766,
        "longitude": -0.088602
    },
    {
        "title": "Hackathon",
        "capacity": 30,
        "image": "https://images.freeimages.com/images/large-previews/b13/writing-on-laptop-1153506.jpg",
        "date": "2nd of February at 2pm",
        "latitude": 51.525222,
        "longitude": -0.080842
    }
]